OneNeuron/__init__.py
OneNeuron/perceptron.py
OneNeuron_pypi_KarthikArumugam3-0.0.3.dist-info/LICENSE
OneNeuron_pypi_KarthikArumugam3-0.0.3.dist-info/METADATA
OneNeuron_pypi_KarthikArumugam3-0.0.3.dist-info/WHEEL
OneNeuron_pypi_KarthikArumugam3-0.0.3.dist-info/top_level.txt
OneNeuron_pypi_KarthikArumugam3-0.0.3.dist-info/RECORD
